{
  "project_info": {
    "project_number": "472952145512",
    "project_id": "apkmanagerdev",
    "storage_bucket": "apkmanagerdev.appspot.com"
  },
  "client": [
    {
      "client_info": {
        "mobilesdk_app_id": "1:472952145512:android:cc2879573851755118dddd",
        "android_client_info": {
          "package_name": "dev.solucionesdigitalesapps.apkmanager.dev"
        }
      },
      "oauth_client": [],
      "api_key": [
        {
          "current_key": "AIzaSyBOUNGfbfylSeqWC-w2Ffa7tb-jbcfsVuI"
        }
      ],
      "services": {
        "appinvite_service": {
          "other_platform_oauth_client": []
        }
      }
    }
  ],
  "configuration_version": "1"
}